samplestring/__init__.py
samplestring/stringutil.py
samplestring-0.1.1.dist-info/WHEEL
samplestring-0.1.1.dist-info/entry_points.txt
samplestring-0.1.1.dist-info/METADATA
samplestring-0.1.1.dist-info/RECORD
