Metadata-Version: 2.3
Name: samplestring
Version: 0.1.1
Summary: Easy sample for string
Requires-Python: >=3.13
